client.py
config.py
setup.py
./client.py
./config.py
./interceptors/__init__.py
./interceptors/interceptor.py
./interceptors/metadata_interceptor.py
interceptors/__init__.py
interceptors/interceptor.py
interceptors/metadata_interceptor.py
util_searchads360_hm.egg-info/PKG-INFO
util_searchads360_hm.egg-info/SOURCES.txt
util_searchads360_hm.egg-info/dependency_links.txt
util_searchads360_hm.egg-info/top_level.txt